django_sched/__init__.py
django_sched/admin.py
django_sched/apps.py
django_sched/models.py
django_sched/sched.py
django_sched/signals.py
django_sched/tests.py
django_sched/views.py
django_sched/migrations/0001_initial.py
django_sched/migrations/__init__.py
django_sched-0.1.3.dist-info/licenses/LICENSE
django_sched-0.1.3.dist-info/METADATA
django_sched-0.1.3.dist-info/WHEEL
django_sched-0.1.3.dist-info/top_level.txt
django_sched-0.1.3.dist-info/RECORD
