Metadata-Version: 2.4
Name: django-sched
Version: 0.1.3
Summary: 轻量级的 Django 定时任务调度框架，基于数据库锁实现进程/线程级调度与日志记录。
Author: cone387
Project-URL: Homepage, https://github.com/cone387/DjangoSched.git
Project-URL: Repository, https://github.com/cone387/DjangoSched.git
Keywords: django,scheduler,cron,task
Requires-Python: >=3.13
License-File: LICENSE
Requires-Dist: django>=5.0
Dynamic: license-file
